Experiment6/shift_register/top.v
`default_nettype none
module top(clk, sel, cin, data_in, data_out);
    input wire clk;
    input wire [2:0] sel;
    input wire cin;
    input reg [7:0] data_in;
    reg [6:0] mem;
    reg [2:0] cnt;
    output reg [7:0] data_out;

    always @(posedge clk)
    begin
        case(sel)
            3'b000: data_out <= 8'b0;
            3'b001: data_out <= data_in;
            3'b010: data_out <= {1'b0, data_out[7:1]};
            3'b011: data_out <= {data_out[6:0], 1'b0};
            3'b100: data_out <= {data_out[7], data_out[7:1]};
            3'b101: 
            begin
                if(cnt == 3'b111)
                begin
                    data_out[7-cnt] <= cin;
                    data_out[7:1] <= mem[6:0];
                    cnt <= 0;
                end
                else
                begin
                    mem[7-cnt] <= cin;
                    cnt <= cnt + 1;
                end
            end
            3'b110: data_out <= {data_out[0], data_out[7:1]};
            3'b111: data_out <= {data_out[6:0], data_out[7]};
            default: data_out <= 8'b0;
        endcase
    end
endmodule

Experiment6/shift_register/dump.vcd
$version Generated by VerilatedVcd $end
$timescale 1s $end

 $scope module TOP $end
  $var wire  1 % cin $end
  $var wire  1 # clk $end
  $var wire  8 & data_in [7:0] $end
  $var wire  8 ' data_out [7:0] $end
  $var wire  3 $ sel [2:0] $end
  $scope module top $end
   $var wire  1 % cin $end
   $var wire  1 # clk $end
   $var wire  3 ) cnt [2:0] $end
   $var wire  8 & data_in [7:0] $end
   $var wire  8 ' data_out [7:0] $end
   $var wire  7 ( mem [6:0] $end
   $var wire  3 $ sel [2:0] $end
  $upscope $end
 $upscope $end
$enddefinitions $end


#1
0#
b001 $
0%
b10101110 &
b00000000 '
b0000000 (
b000 )
#2
1#
b10101110 '
#3
0#
b010 $
b00000000 &
#4
1#
b01010111 '
#5
0#
b100 $
#6
1#
b00101011 '
#7
0#
b101 $
1%
#8
1#
b001 )
#9
0#
0%
#10
1#
b010 )
#11
0#
1%
#12
1#
b0100000 (
b011 )
#13
0#
0%
#14
1#
b100 )
#15
0#
1%
#16
1#
b0101000 (
b101 )
#17
0#
0%
#18
1#
b110 )
#19
0#
1%
#20
1#
b0101010 (
b111 )
#21
0#
0%
#22
1#
b01010100 '
b000 )
#23
0#
b110 $
#24
1#
b00101010 '
#25
0#
b111 $
#26
1#
b01010100 '
#27
0#
b000 $
#28
1#
b00000000 '
