Experiment3/simple_add_sub/top.v
`default_nettype none
module top(a, b, cin, pcarry, carry, zero, overflow, result);
    input wire signed [31:0] a, b;
    input wire cin, pcarry;
    output wire carry, zero, overflow;
    output wire signed [31:0] result;
/* verilator lint_off WIDTHEXPAND */
    assign {carry, result} = cin ? a + ({32{cin}}^b) + cin + pcarry : a + b + pcarry;
    assign overflow = cin ? (a[31] == (cin^b[31])) && (result[31] != a[31]) : (a[31] == b[31]) && (result[31] != a[31]);
    assign zero = ~(| result);
/* verilator lint_on WIDTHEXPAND */
endmodule

/*        case(cin)
            1'b0: 
                begin
                  assign {carry, result} = a + b + pcarry;
                  assign overflow = (a[31] == b[31]) && (result[31] != a[31]);
                  assign zero = ~(| result);
                end
            1'b1:
                begin 
                  assign {carry,result} = a + ({32{cin}}^b) + cin + pcarry;
                  assign overflow = (a[31] == (cin^b[31])) && (result[31] != a[31]);
                  assign zero = ~(| result);
                end
        endcase
*/

Experiment3/simple_add_sub/dump.vcd
$version Generated by VerilatedVcd $end
$timescale 1s $end

 $scope module TOP $end
  $var wire 32 # a [31:0] $end
  $var wire 32 $ b [31:0] $end
  $var wire  1 ' carry $end
  $var wire  1 % cin $end
  $var wire  1 ) overflow $end
  $var wire  1 & pcarry $end
  $var wire 32 * result [31:0] $end
  $var wire  1 ( zero $end
  $scope module top $end
   $var wire 32 # a [31:0] $end
   $var wire 32 $ b [31:0] $end
   $var wire  1 ' carry $end
   $var wire  1 % cin $end
   $var wire  1 ) overflow $end
   $var wire  1 & pcarry $end
   $var wire 32 * result [31:0] $end
   $var wire  1 ( zero $end
  $upscope $end
 $upscope $end
$enddefinitions $end


#1
b00000000000000000000000000000001 #
b00000000000000000000000000000001 $
0%
0&
0'
0(
0)
b00000000000000000000000000000010 *
#2
1%
1'
1(
b00000000000000000000000000000000 *
#3
1&
0(
b00000000000000000000000000000001 *
#4
0%
0'
b00000000000000000000000000000011 *
#5
b10000000000000000000000000000001 $
0&
b10000000000000000000000000000010 *
#6
1%
1)
b10000000000000000000000000000000 *
#7
1&
b10000000000000000000000000000001 *
#8
0%
0)
b10000000000000000000000000000011 *
#9
b00000000000000000000000000000000 #
b00000000000000000000000000000000 $
0&
1(
b00000000000000000000000000000000 *
#10
b01111111111111111111111111111111 #
b01111111111111111111111111111111 $
1&
0(
1)
b11111111111111111111111111111111 *
#11
0&
b11111111111111111111111111111110 *
#12
1%
1&
1'
0)
b00000000000000000000000000000001 *
