Experiment3/ALU/top.v
`default_nettype none
module top(a, b, sel, res, overflow);
    input wire signed [31:0] a, b;
    input wire [3:0] sel;
    output reg overflow;
    output reg signed [31:0] res;
/* verilator lint_off LATCH */
    always @(*)
    begin
        case (sel)
            4'b0001: 
            begin
                overflow = 0;
                res = a + b;
                overflow = (a[31] == b[31]) && (res[31] != a[31]);
            end
            4'b0010: 
            begin
                overflow = 0;
                res = a + (~b + 1);
                overflow = (a[31] != b[31]) && (res[31] != a[31]);
            end
            4'b0011: 
            begin
                overflow = 0;
                res = a ^ b;
            end
            4'b0100: 
            begin
                overflow = 0;
                res = a & b;
            end
            4'b0101: 
            begin
                overflow = 0;
                res = a | b;
            end
            4'b0110: 
            begin
                overflow = 0;
                res = {res[30:0], 1'b0};
            end
            4'b0111: 
            begin
                overflow = 0;
                res = {1'b0, res[31:1]};
            end
            4'b1000: 
            begin
                overflow = 0;
                res = {res[31], res[31:1]};
            end
            4'b1001:
            begin
                overflow = 0;
                res = a + (~b + 1);
                res = res[31] ? 32'b1 : 32'b0;  //less than output 1, else 0
            end
            default:
                res = 32'b0; 
        endcase
    end
/* verilator lint_on LATCH */
endmodule

Experiment3/ALU/dump.vcd
$version Generated by VerilatedVcd $end
$timescale 1s $end

 $scope module TOP $end
  $var wire 32 # a [31:0] $end
  $var wire 32 $ b [31:0] $end
  $var wire  1 & overflow $end
  $var wire 32 ' res [31:0] $end
  $var wire  4 % sel [3:0] $end
  $scope module top $end
   $var wire 32 # a [31:0] $end
   $var wire 32 $ b [31:0] $end
   $var wire  1 & overflow $end
   $var wire 32 ' res [31:0] $end
   $var wire  4 % sel [3:0] $end
  $upscope $end
 $upscope $end
$enddefinitions $end


#1
b00000000000000000000000000000001 #
b00000000000000000000000000000001 $
b0001 %
0&
b00000000000000000000000000000010 '
#2
b0010 %
b00000000000000000000000000000000 '
#3
b0011 %
#4
b0100 %
b00000000000000000000000000000001 '
#5
b0101 %
#6
b0110 %
b00000000000000000000000000000010 '
#7
b0111 %
b00000000000000000000000000000001 '
#8
b1000 %
b00000000000000000000000000000000 '
#9
b1001 %
