Experiment2/Decoder/top.v
`default_nettype none
module top(x, en, y);
    input wire [1:0] x;
    input en;
    output reg [3:0] y;

    always @(x or en)
        if(en)
        begin
            case (x)
                2'd0: y = 4'b0001;
                2'd1: y = 4'b0010;
                2'd2: y = 4'b0100;
                2'd3: y = 4'b1000;
                default: y = 4'b0000;
            endcase
        end
        else
            y = 4'b0000;

endmodule

Experiment2/Decoder/dump.vcd
$version Generated by VerilatedVcd $end
$timescale 1s $end

 $scope module TOP $end
  $var wire  1 $ en $end
  $var wire  2 # x [1:0] $end
  $var wire  4 % y [3:0] $end
  $scope module top $end
   $var wire  1 $ en $end
   $var wire  2 # x [1:0] $end
   $var wire  4 % y [3:0] $end
  $upscope $end
 $upscope $end
$enddefinitions $end


#1
b00 #
0$
b0000 %
#2
b01 #
#3
b10 #
#4
b11 #
#5
b00 #
1$
b0001 %
#6
b01 #
b0010 %
#7
b10 #
b0100 %
#8
b11 #
b1000 %
