Experiment1/BinarySelector/m_mux21.v
`default_nettype none
module m_mux21(a,b,s,y);
  input wire a,b,s;    
  output wire y;       

  assign  y = (~s&a)|(s&b);  

endmodule

Experiment1/BinarySelector/dump.vcd
$version Generated by VerilatedVcd $end
$timescale 1s $end

 $scope module TOP $end
  $var wire  1 # a $end
  $var wire  1 $ b $end
  $var wire  1 % s $end
  $var wire  1 & y $end
  $scope module m_mux21 $end
   $var wire  1 # a $end
   $var wire  1 $ b $end
   $var wire  1 % s $end
   $var wire  1 & y $end
  $upscope $end
 $upscope $end
$enddefinitions $end


#1
0#
0$
0%
0&
#2
1$
#3
1#
0$
1&
#4
1$
#5
0#
0$
1%
0&
#6
1$
1&
#7
1#
0$
0&
#8
1$
1&
