Experiment1/MultipleQuadSelector/top.v
`default_nettype none
module top(a,s,y);
    input wire [3:0] a;
    input wire [1:0] s;
    output reg y;

    always @ (s or a)
        case (s)
            0: y = a[0];
            1: y = a[1];
            2: y = a[2];
            3: y = a[3];
            default: y = 1'b0;
        endcase

endmodule

Experiment1/MultipleQuadSelector/dump.vcd
$version Generated by VerilatedVcd $end
$timescale 1s $end

 $scope module TOP $end
  $var wire  4 # a [3:0] $end
  $var wire  2 $ s [1:0] $end
  $var wire  1 % y $end
  $scope module top $end
   $var wire  4 # a [3:0] $end
   $var wire  2 $ s [1:0] $end
   $var wire  1 % y $end
  $upscope $end
 $upscope $end
$enddefinitions $end


#1
b1110 #
b00 $
0%
#2
b0001 #
1%
#3
b1110 #
b01 $
#4
b0010 #
#5
b1010 #
b10 $
0%
#6
b0100 #
1%
#7
b0111 #
b11 $
0%
#8
b1001 #
1%
