Experiment6/barrel_shifter/top.v
`default_nettype none
module top(din, shamt, LorR, AorL, dout);
    input wire [7:0] din;
    input wire [2:0] shamt;
    input wire LorR, AorL;
    output reg [7:0] dout;
    reg [7:0] tmp;

    always @(din or shamt or LorR or AorL)
    begin
        case(AorL)
            1'b0: case(LorR)
                    1'b1:
                    begin
                        tmp <= shamt[0] ? {din[6:0], 1'b0} : tmp;
                        tmp <= shamt[1] ? {din[5:0], 2'b0} : tmp;
                        tmp <= shamt[2] ? {din[3:0], 4'b0} : tmp;
                    end
                    1'b0:
                    begin
                        tmp <= shamt[0] ? {1'b0, din[7:1]} : tmp;
                        tmp <= shamt[1] ? {2'b0, din[7:2]} : tmp;
                        tmp <= shamt[2] ? {4'b0, din[7:4]} : tmp;
                    end
                  endcase
            1'b1: case(LorR)
                  1'b1:
                    begin
                        tmp <= shamt[0] ? {din[6:0], 1'b0} : tmp;
                        tmp <= shamt[1] ? {din[5:0], 2'b0} : tmp;
                        tmp <= shamt[2] ? {din[3:0], 4'b0} : tmp;
                    end
                  1'b0:
                    begin
                        tmp <= shamt[0] ? {din[7], din[7:1]} : tmp;
                        tmp <= shamt[1] ? {{2{din[7]}}, din[7:2]} : tmp;
                        tmp <= shamt[2] ? {{4{din[7]}}, din[7:4]} : tmp;
                    end
            endcase
        endcase
        dout <= tmp;
    end
endmodule

Experiment6/barrel_shifter/dump.vcd
$version Generated by VerilatedVcd $end
$timescale 1s $end

 $scope module TOP $end
  $var wire  1 & AorL $end
  $var wire  1 % LorR $end
  $var wire  8 # din [7:0] $end
  $var wire  8 ' dout [7:0] $end
  $var wire  3 $ shamt [2:0] $end
  $scope module top $end
   $var wire  1 & AorL $end
   $var wire  1 % LorR $end
   $var wire  8 # din [7:0] $end
   $var wire  8 ' dout [7:0] $end
   $var wire  3 $ shamt [2:0] $end
   $var wire  8 ( tmp [7:0] $end
  $upscope $end
 $upscope $end
$enddefinitions $end


#1
b10101110 #
b001 $
0%
0&
b00000000 '
b00000000 (
#2
1%
#3
0%
1&
#4
1%
#5
b010 $
0%
0&
#6
1%
#7
0%
1&
#8
1%
#9
b100 $
0%
0&
b00001010 (
#10
1%
b00001010 '
b11100000 (
#11
0%
1&
b11100000 '
b11111010 (
#12
1%
b11111010 '
b11100000 (
