Experiment2/Opencoder/top.v
`default_nettype none
module top(x,en,y);
  input wire [3:0] x;
  input  en;
  output reg [1:0] y;
  integer i;
  always @(x or en) begin
    if (en) begin
      y = 0;
      for( i = 0; i <= 3; i = i+1)
          if(x[i] == 1)  y = i[1:0];
    end
    else  y = 0;
  end
endmodule

Experiment2/Opencoder/dump.vcd
$version Generated by VerilatedVcd $end
$timescale 1s $end

 $scope module TOP $end
  $var wire  1 $ en $end
  $var wire  4 # x [3:0] $end
  $var wire  2 % y [1:0] $end
  $scope module top $end
   $var wire  1 $ en $end
   $var wire 32 & i [31:0] $end
   $var wire  4 # x [3:0] $end
   $var wire  2 % y [1:0] $end
  $upscope $end
 $upscope $end
$enddefinitions $end


#1
b0000 #
0$
b00 %
b00000000000000000000000000000000 &
#2
b0001 #
#3
b0010 #
#4
b0011 #
#5
b0100 #
#6
b0101 #
#7
b0110 #
#8
b0111 #
#9
b1000 #
#10
b0000 #
1$
b00000000000000000000000000000100 &
#11
b0001 #
#12
b0010 #
b01 %
#13
b0011 #
#14
b0100 #
b10 %
#15
b0101 #
#16
b0110 #
#17
b0111 #
#18
b1000 #
b11 %
